tests/__init__.py
tests/test_core.py
xsrandom/__all__.py
xsrandom/__init__.py
xsrandom/core.py
xsrandom/crypto.py
xsrandom/datetime.py
xsrandom/distributions.py
xsrandom/geo.py
xsrandom/sequences.py
xsrandom/strings.py
xsrandom-0.1.0.dist-info/licenses/LICENSE
xsrandom-0.1.0.dist-info/METADATA
xsrandom-0.1.0.dist-info/WHEEL
xsrandom-0.1.0.dist-info/top_level.txt
xsrandom-0.1.0.dist-info/RECORD
